Workbook
Name rendimento: App!$C$13
Name salario: App!$C$12
Name sugestao_investimento: App!$C$14

Sheet App
B11: Configurações
B12: Salário | C12: 5000
B13: Rendimento Carteira | C13: 0.01
B14: Sugestão de Investimento | C14: 1500
B16: INVESTIMENTO MENSAL
B17: Quanto investor por mês? | C17: =(salario)*0.3 -> 1500
A18: 2 | B18: Por quantos anos? | C18: 5
A19: 5 | B19: Taxa de rendimento? | C19: 0.0108
A20: 10 | B20: Patrimonio acumulado? | C20: =FV(C19,C18*12,C17*-1) -> 125706.03
A21: 20 | B21: Dividendos mensais? | C21: =C20*C13 -> 1257.0603
A22: 30
B23: CENÁRIOS | D23: Dividendo
B24: Projeção para 2 anos: | C24: =FV($C$19,$A18*12,$C$17*-1) -> 40846.295 | D24: =C24*rendimento -> 408.46295
B25: Projeção para 5 anos: | C25: =FV($C$19,$A19*12,$C$17*-1) -> 125706.03 | D25: =C25*rendimento -> 1257.0603
B26: Projeção para 10 anos: | C26: =FV($C$19,$A20*12,$C$17*-1) -> 365186.5 | D26: =C26*rendimento -> 3651.865
B27: Projeção para 20 anos: | C27: =FV($C$19,$A21*12,$C$17*-1) -> 1690573.5 | D27: =C27*rendimento -> 16905.735
B28: Projeção para 30 anos: | C28: =FV($C$19,$A22*12,$C$17*-1) -> 6500857.2 | D28: =C28*rendimento -> 65008.572
B30: PERFIL | C30: Agressivo
B31: VALOR A SER INVESTIDO POR MÊS | C31: =sugestao_investimento -> 1500
B33: TIPO FII | C33: Percentual sugerido | D33: Valores
B34: PAPEL | C34: =VLOOKUP($C$30&"-"&B34,Sheet2!$A:$D,4,FALSE) -> 0.5 | D34: =$C$31*C34 -> 750
B35: TIJOLO | C35: =VLOOKUP($C$30&"-"&B35,Sheet2!$A:$D,4,FALSE) -> 0.1 | D35: =$C$31*C35 -> 150
B36: HÍBRIDOS | C36: =VLOOKUP($C$30&"-"&B36,Sheet2!$A:$D,4,FALSE) -> 0.1 | D36: =$C$31*C36 -> 150
B37: FOFS | C37: =VLOOKUP($C$30&"-"&B37,Sheet2!$A:$D,4,FALSE) -> 0.2 | D37: =$C$31*C37 -> 300
B38: DESENVOLVIMENTO | C38: =VLOOKUP($C$30&"-"&B38,Sheet2!$A:$D,4,FALSE) -> 0.05 | D38: =$C$31*C38 -> 75
B39: HOTELARIA | C39: =VLOOKUP($C$30&"-"&B39,Sheet2!$A:$D,4,FALSE) -> 0.05 | D39: =$C$31*C39 -> 75

Sheet Sheet2
A4: CHAVE | B4: PERFIL | C4: TIPO DE FII | D4: %
A5: =B5&"-"&C5 -> Conservador -PAPEL | B5: Conservador | C5: PAPEL | D5: 0.3
A6: =B6&"-"&C6 -> Conservador -TIJOLO | B6: Conservador | C6: TIJOLO | D6: 0.5
A7: =B7&"-"&C7 -> Conservador -HÍBRIDOS | B7: Conservador | C7: HÍBRIDOS | D7: 0.1
A8: =B8&"-"&C8 -> Conservador -FOFS | B8: Conservador | C8: FOFS | D8: 0.1
A9: =B9&"-"&C9 -> Conservador -DESENVOLVIMENTO | B9: Conservador | C9: DESENVOLVIMENTO | D9: 0
A10: =B10&"-"&C10 -> Conservador -HOTELARIA | B10: Conservador | C10: HOTELARIA | D10: 0
A11: =B11&"-"&C11 -> Moderador-PAPEL | B11: Moderador | C11: PAPEL | D11: 0.32
A12: =B12&"-"&C12 -> Moderador-TIJOLO | B12: Moderador | C12: TIJOLO | D12: 0.4
A13: =B13&"-"&C13 -> Moderador-HÍBRIDOS | B13: Moderador | C13: HÍBRIDOS | D13: 0.03
A14: =B14&"-"&C14 -> Moderador-FOFS | B14: Moderador | C14: FOFS | D14: 0.1
A15: =B15&"-"&C15 -> Moderador-DESENVOLVIMENTO | B15: Moderador | C15: DESENVOLVIMENTO | D15: 0.1
A16: =B16&"-"&C16 -> Moderador-HOTELARIA | B16: Moderador | C16: HOTELARIA | D16: 0.05
... A22: =B22&"-"&C22 -> Agressivo-HOTELARIA | B22: Agressivo | C22: HOTELARIA | D22: 0.05
